{"Тип графического адаптера":"интегрированный","Наличие NumPad":"Нет","Вес, в килограммах":"1.29","Разрешение экрана":"2560x1600","Ширина, в сантиметрах":"30.41","Модель процессора":"M1","Встроенные динамики":"Да","Назначение":"универсальный","Сенсорный дисплей":"Нет","Поверхность экрана":"глянцевая","Интерфейсы ноутбука":"Thunderbolt 3 - 2; Гибридный разъем наушники/микрофон 3.5мм - 1","Тип аккумулятора":"Li-pol","Характеристики":"Можно сравнить с другими товарами","Стандарты Wi-Fi":"IEEE 802.11 a/ac/b/g/n/ax","Встроенный микрофон":"Да","Поддержка Wi-Fi":"Да","Бренд":"Apple","Операционная система":"Mac OS","Объем SSD, в гигабайтах":"512","price":"129 890 ₽","Цвет корпуса":"серый","Встроенная веб-камера":"Да","Оптический привод":"отсутствует","Объем оперативной памяти, в гигабайтах":"8","Артикул производителя":"Z1240004J","Высота, в сантиметрах":"21.24","Интерфейс SSD":"M.2","Раскладка клавиатуры":"RU","Материал корпуса":"металл","Толщина, в сантиметрах":"1.61","Технология дисплея":"Retina","Диагональ дисплея, в дюймах":"13.3","Объем жесткого диска HDD, в гигабайтах":"0","Поддержка Bluetooth":"Да","Тип памяти":"Apple M1","Производитель процессора":"Apple","Объем видеопамяти, в гигабайтах":"SMA","Производитель графического адаптера":"Apple","Картридер":"Нет","Версия Bluetooth":"5.0","name":"Ноутбук Apple MacBook Air 13 M1/8Gb/512Gb (Z1240004J)","Код товара":"100029273461","Тип":"ноутбук","Серия процессора":"M1","Количество ядер процессора":"8","Модель графического процессора":"M1","Год релиза":"2020","Модель":"MacBook Air 13"}