{"Тип графического адаптера":"дискретный","Частота памяти, в мегагерцах":"3200","Наличие NumPad":"Нет","Вес, в килограммах":"1.46","Максимальный объем оперативной памяти, в гигабайтах":"256","Разрешение экрана":"1920x1080","Ширина, в сантиметрах":"22.5","Модель процессора":"1255U","Встроенные динамики":"Да","Назначение":"для работы и учебы","Сенсорный дисплей":"Нет","Поверхность экрана":"антибликовая","Интерфейсы ноутбука":"USB 3.2 Type-A - 2; Разъем для микрофона 3.5мм - 1; Разъем для наушников 3.5мм - 1","Характеристики":"Можно сравнить с другими товарами","Встроенный микрофон":"Да","Поддержка Wi-Fi":"Да","Бренд":"HP","Операционная система":"DOS","Объем SSD, в гигабайтах":"1024","price":"82 140 ₽","Тактовая частота процессора, в гигагерцах":"4.7","Цвет корпуса":"темно-серый","Встроенная веб-камера":"Да","Оптический привод":"отсутствует","Объем оперативной памяти, в гигабайтах":"16","Качество видеозаписи":"720p HD","Маркетинговый цвет":"металлическое серебро","Высота, в сантиметрах":"22.5","Толщина, в сантиметрах":"1.46","Технология дисплея":"IPS","Диагональ дисплея, в дюймах":"14","Подсветка клавиатуры":"Да","Объем жесткого диска HDD, в гигабайтах":"0","Поддержка Bluetooth":"Да","Максимальное время работы, в часах":"5","Тип памяти":"DDR4","Водонепроницаемая клавиатура":"Нет","Производитель процессора":"Intel","Объем видеопамяти, в гигабайтах":"SMA","Производитель графического адаптера":"Intel","Картридер":"Нет","Версия Bluetooth":"5.0","name":"Ноутбук HP 14s-dq5011nm","Код товара":"100047805429","Тип":"ноутбук","Серия процессора":"Core i7","Количество ядер процессора":"10","Модель графического процессора":"Iris Xe Graphics"}