{"Частота памяти, в мегагерцах":"3200","Вес, в килограммах":"1.86","Ширина, в сантиметрах":"35.9","Модель процессора":"1135G7","Встроенные динамики":"Да","Сенсорный дисплей":"Нет","Поверхность экрана":"матовая","Интерфейсы ноутбука":"HDMI - 1; USB 3.0 Type-A - 3; USB 3.0 Type-C - 1; Гибридный разъем наушники/микрофон 3.5мм - 1","Встроенный микрофон":"Да","Бренд":"Acer","Операционная система":"Windows","price":"60 157 ₽","Тактовая частота процессора, в гигагерцах":"2.4","Сетевой адаптер":"10/100/1000 Мбит/сек","Маркетинговый цвет":"серебристый","Возможность расширения оперативной памяти":"Да","Толщина, в сантиметрах":"2.17","Технология дисплея":"TN","Тип памяти":"DDR4","Производитель графического адаптера":"NVIDIA","name":"Ноутбук Acer A315-58 Silver (NX.ADDEX.01E)","Код товара":"100047346100","Тип":"ноутбук","Количество ядер процессора":"4","Модель":"A315-58","Максимальная тактовая частота, в гигагерцах":"4.2","Тип графического адаптера":"дискретный","Наличие NumPad":"Нет","Максимальный объем оперативной памяти, в гигабайтах":"12","Разрешение экрана":"1920x1080","Назначение":"универсальный","Тип аккумулятора":"Li-ion","Характеристики":"Можно сравнить с другими товарами","Стандарты Wi-Fi":"802.11ac","Поддержка Wi-Fi":"Да","Версия операционной системы":"11 Home","Объем SSD, в гигабайтах":"0","Цвет корпуса":"серебристый","Встроенная веб-камера":"Да","Оптический привод":"отсутствует","Объем оперативной памяти, в гигабайтах":"8","Артикул производителя":"NX.ADDEX.01E","Высота, в сантиметрах":"2.17","Чипсет":"SoC","Интерфейс SSD":"M.2","Объем HDD+SSD, в гигабайтах":"1000","Раскладка клавиатуры":"EU; RU","Материал корпуса":"алюминий","Диагональ дисплея, в дюймах":"15.6","Подсветка клавиатуры":"Да","Объем жесткого диска HDD, в гигабайтах":"1024","Поддержка Bluetooth":"Да","Максимальное время работы, в часах":"8","Водонепроницаемая клавиатура":"Да","Производитель процессора":"Intel","Объем видеопамяти, в гигабайтах":"2","Картридер":"Нет","Версия Bluetooth":"5.0","Серия процессора":"Core i5","Модель графического процессора":"GeForce MX350","Частота обновления, в Гц":"60"}