{"Вес, в килограммах":"2.36","Ширина, в сантиметрах":"35.89","Модель процессора":"12650H","Встроенные динамики":"Да","Сенсорный дисплей":"Нет","Поверхность экрана":"матовая","Интерфейсы ноутбука":"HDMI; RJ-45 - 1; USB 3.1 Type-A - 3; USB 3.2 Gen1 - 1","Встроенный микрофон":"Да","Бренд":"Hasee","Операционная система":"DOS","price":"88 245 ₽ 95 084 ₽","Тактовая частота процессора, в гигагерцах":"2.3","Толщина, в сантиметрах":"2.65","Технология дисплея":"IPS","Тип памяти":"DDR4","Производитель графического адаптера":"NVIDIA","name":"Ноутбук Hasee S8-DA7NS черный (156145)","Код товара":"600009709763","Тип":"ноутбук","Количество ядер процессора":"10","Модель":"S8-DA7NS","Тип графического адаптера":"дискретный","Наличие NumPad":"Да","Разрешение экрана":"1920x1080","Назначение":"игровой","Характеристики":"Можно сравнить с другими товарами","Стандарты Wi-Fi":"802.11 ax","Поддержка Wi-Fi":"Да","Объем SSD, в гигабайтах":"512","Цвет корпуса":"черный","Встроенная веб-камера":"Да","Оптический привод":"отсутствует","Объем оперативной памяти, в гигабайтах":"16","Артикул производителя":"156145","Высота, в сантиметрах":"25.75","Раскладка клавиатуры":"EU; RU","Материал корпуса":"металл; пластик","Диагональ дисплея, в дюймах":"15.6","Подсветка клавиатуры":"Да","Объем жесткого диска HDD, в гигабайтах":"0","Поддержка Bluetooth":"Да","Максимальное время работы, в часах":"7","Производитель процессора":"Intel","Объем видеопамяти, в гигабайтах":"6","Картридер":"Нет","Версия Bluetooth":"5.2","Серия процессора":"Core i7","Модель графического процессора":"GeForce RTX 3060","Год релиза":"2022","Разрешение матрицы веб-камеры, в мегапикселях":"0.9","Частота обновления, в Гц":"144"}