{"Частота памяти, в мегагерцах":"3200","Вес, в килограммах":"2.3","Ширина, в сантиметрах":"35.9","Модель процессора":"10300H","Встроенные динамики":"Да","Сенсорный дисплей":"Нет","Интерфейсы ноутбука":"HDMI - 1; USB 2.0 Type-A - 1; USB 3.2 Type-A - 2; USB 3.2 Type-C - 1; Гибридный разъем наушники/микрофон 3.5мм - 1; RJ-45 - 1","Встроенный микрофон":"Да","Бренд":"ASUS","Операционная система":"Без ОС","price":"60 411 ₽ 69 395 ₽","Тактовая частота процессора, в гигагерцах":"2.5","Сетевой адаптер":"10/100/1000 Мбит/сек","Fusion Drive":"Нет","Толщина, в сантиметрах":"2.49","Технология дисплея":"IPS","Тип памяти":"DDR4","Производитель графического адаптера":"NVIDIA","name":"Ноутбук Asus TUF Gaming F15 FX506LHB-HN323 Grey (90NR03U2-M007N0)","Код товара":"100043880456","Тип":"ноутбук","Количество ядер процессора":"4","Модель":"TUF Gaming F15 FX506LHB-HN323","Тип графического адаптера":"дискретный","Наличие NumPad":"Да","Разрешение экрана":"1920x1080","Назначение":"игровой","Характеристики":"Можно сравнить с другими товарами","Поддержка Wi-Fi":"Да","Объем SSD, в гигабайтах":"512","Технология Miracast":"Нет","Цвет корпуса":"серый","Встроенная веб-камера":"Да","Оптический привод":"отсутствует","Объем оперативной памяти, в гигабайтах":"8","Артикул производителя":"90NR03U2-M007N0","Высота, в сантиметрах":"25.6","Раскладка клавиатуры":"EU; RU","Материал корпуса":"пластик","Диагональ дисплея, в дюймах":"15.6","Подсветка клавиатуры":"Да","Объем жесткого диска HDD, в гигабайтах":"0","Поддержка Bluetooth":"Да","Максимальное время работы, в часах":"6","Водонепроницаемая клавиатура":"Нет","Производитель процессора":"Intel","Объем видеопамяти, в гигабайтах":"4","Картридер":"Нет","Серия процессора":"Core i5","Модель графического процессора":"GeForce GTX 1650","Частота обновления, в Гц":"144"}