{"Частота памяти, в мегагерцах":"3200","Вес, в килограммах":"1.74","Ширина, в сантиметрах":"35.8","Модель процессора":"5500U","Встроенные динамики":"Да","Сенсорный дисплей":"Нет","Интерфейсы ноутбука":"HDMI - 1; USB 3.0 Type-A - 2; USB 3.1 Type-A - 1; USB 3.2 Type-A - 2; USB 3.2 Type-C - 2; USB 3.1 Type-C - 1; RJ-45 - 1; Гибридный разъем наушники/микрофон 3.5мм - 1","Встроенный микрофон":"Да","Бренд":"HP","Операционная система":"DOS","price":"50 909 ₽","Тактовая частота процессора, в гигагерцах":"2.1","Сетевой адаптер":"10/100/1000 Мбит/сек","Возможность расширения оперативной памяти":"Да","Fusion Drive":"Нет","Толщина, в сантиметрах":"24.2","Технология дисплея":"IPS","Тип памяти":"DDR4","Производитель графического адаптера":"AMD","name":"Ноутбук HP 255 G8 (45M81ES)","Код товара":"600004948961","Тип":"ноутбук","Количество ядер процессора":"6","Модель":"255 G8","Тип графического адаптера":"интегрированный","Наличие NumPad":"Да","Максимальный объем оперативной памяти, в гигабайтах":"16","Разрешение экрана":"1920x1080","Назначение":"для работы и учебы","Характеристики":"Можно сравнить с другими товарами","Поддержка Wi-Fi":"Да","Объем SSD, в гигабайтах":"256","Технология Miracast":"Нет","Цвет корпуса":"черный; серый","Встроенная веб-камера":"Да","Оптический привод":"отсутствует","Объем оперативной памяти, в гигабайтах":"8","Артикул производителя":"45M81ES","Высота, в сантиметрах":"1.99","Объем HDD+SSD, в гигабайтах":"256","Раскладка клавиатуры":"RU","Материал корпуса":"пластик","Диагональ дисплея, в дюймах":"15.6","Объем жесткого диска HDD, в гигабайтах":"0","Поддержка Bluetooth":"Да","Максимальное время работы, в часах":"9","Водонепроницаемая клавиатура":"Нет","Производитель процессора":"AMD","Объем видеопамяти, в гигабайтах":"SMA","Картридер":"Да","Серия процессора":"Ryzen 5","Модель графического процессора":"Radeon Graphics","Частота обновления, в Гц":"60"}