{"Частота памяти, в мегагерцах":"3200","Вес, в килограммах":"1.86","Ширина, в сантиметрах":"35.9","Модель процессора":"11400H","Встроенные динамики":"Да","Сенсорный дисплей":"Нет","Поверхность экрана":"матовая","Интерфейсы ноутбука":"HDMI - 1; RJ-45 - 1; USB 3.2 Type-A - 3; USB 3.2 Type-C - 1; Гибридный разъем наушники/микрофон 3.5мм - 1","Встроенный микрофон":"Да","Бренд":"MSI","Операционная система":"DOS","price":"87 951 ₽","Тактовая частота процессора, в гигагерцах":"2.7","Fusion Drive":"Нет","Толщина, в сантиметрах":"2.17","Технология дисплея":"IPS","Тип памяти":"DDR4","Производитель графического адаптера":"NVIDIA","name":"Ноутбук MSI Thin GF63 11UD-206XRU Black (9S7-16R612-206)","Код товара":"100042617037","Тип":"ноутбук","Количество ядер процессора":"6","Модель":"Thin GF63 11UD-206XRU","Тип графического адаптера":"дискретный","Наличие NumPad":"Нет","Разрешение экрана":"1920x1080","Назначение":"игровой","Характеристики":"Можно сравнить с другими товарами","Поддержка Wi-Fi":"Да","Объем SSD, в гигабайтах":"512","Технология Miracast":"Нет","Цвет корпуса":"черный","Встроенная веб-камера":"Да","Оптический привод":"отсутствует","Объем оперативной памяти, в гигабайтах":"16","Артикул производителя":"9S7-16R612-206","Высота, в сантиметрах":"25.4","Раскладка клавиатуры":"EU","Материал корпуса":"металл; пластик","Диагональ дисплея, в дюймах":"15.6","Подсветка клавиатуры":"Да","Объем жесткого диска HDD, в гигабайтах":"0","Поддержка Bluetooth":"Да","Максимальное время работы, в часах":"6","Водонепроницаемая клавиатура":"Нет","Производитель процессора":"Intel","Объем видеопамяти, в гигабайтах":"4","Картридер":"Нет","Серия процессора":"Core i5","Модель графического процессора":"GeForce RTX 3050 Ti","Частота обновления, в Гц":"144"}