{"Тип графического адаптера":"дискретный","Наличие NumPad":"Да","Вес, в килограммах":"1.7","Разрешение экрана":"1920x1080","Ширина, в сантиметрах":"35.88","Модель процессора":"1135G7","Встроенные динамики":"Да","Назначение":"универсальный","Сенсорный дисплей":"Нет","Интерфейсы ноутбука":"USB 3.0 Type-C - 1","Серия":"DZEN","Характеристики":"Можно сравнить с другими товарами","Встроенный микрофон":"Да","Поддержка Wi-Fi":"Да","Бренд":"HIPER","Операционная система":"DOS","Объем SSD, в гигабайтах":"512","price":"62 207 ₽ 62 299 ₽","Тактовая частота процессора, в гигагерцах":"2.4","Цвет корпуса":"серебристый","Встроенная веб-камера":"Да","Оптический привод":"отсутствует","Объем оперативной памяти, в гигабайтах":"16","Маркетинговый цвет":"Серебристый","Артикул производителя":"7QEKD4OD","Высота, в сантиметрах":"2.14","Fusion Drive":"Нет","Толщина, в сантиметрах":"3","Технология дисплея":"IPS","Диагональ дисплея, в дюймах":"15.6","Объем жесткого диска HDD, в гигабайтах":"0","Поддержка Bluetooth":"Да","Максимальное время работы, в часах":"8","Тип памяти":"DDR4","Производитель процессора":"Intel","Объем видеопамяти, в гигабайтах":"2","Производитель графического адаптера":"NVIDIA","Картридер":"Да","name":"Ноутбук HIPER DZEN MTL1569 серебристый (7QEKD4OD)","Код товара":"600009622549","Тип":"ноутбук","Серия процессора":"Core i5","Количество ядер процессора":"4","Модель графического процессора":"GeForce MX450","Модель":"DZEN MTL1569","Частота обновления, в Гц":"60"}